hatch_conda/__about__.py
hatch_conda/__init__.py
hatch_conda/hooks.py
hatch_conda/plugin.py
hatch_conda-0.5.2.dist-info/METADATA
hatch_conda-0.5.2.dist-info/WHEEL
hatch_conda-0.5.2.dist-info/entry_points.txt
hatch_conda-0.5.2.dist-info/licenses/LICENSE.txt
hatch_conda-0.5.2.dist-info/RECORD
