Metadata-Version: 2.3
Name: hatch-conda
Version: 0.5.2
Summary: Hatch plugin for conda environments
Project-URL: History, https://github.com/OldGrumpyViking/hatch-conda/blob/master/HISTORY.md
Project-URL: Issues, https://github.com/OldGrumpyViking/hatch-conda/issues
Project-URL: Source, https://github.com/OldGrumpyViking/hatch-conda
Author-email: OldGrumpyViking <old.grumpy.viking@hotmail.com>
License-Expression: MIT
License-File: LICENSE.txt
Keywords: conda,environment,hatch,plugin
Classifier: Development Status :: 4 - Beta
Classifier: Framework :: Hatch
Classifier: License :: OSI Approved :: MIT License
Classifier: Programming Language :: Python
Classifier: Programming Language :: Python :: 3.7
Classifier: Programming Language :: Python :: 3.8
Classifier: Programming Language :: Python :: 3.9
Classifier: Programming Language :: Python :: 3.10
Classifier: Programming Language :: Python :: 3.11
Classifier: Programming Language :: Python :: 3.12
Classifier: Programming Language :: Python :: Implementation :: CPython
Classifier: Programming Language :: Python :: Implementation :: PyPy
Requires-Python: >=3.7
Requires-Dist: hatch>=1.2.0
Requires-Dist: hatchling>=1.0.0
Requires-Dist: pexpect~=4.8
